{
  "colorSpaceGroups": null,
  "Colors": [
    {
      "Color": {
        "r": 0.0,
        "g": 0.0,
        "b": 0.0,
        "a": 1.0,
        "r8": 0,
        "g8": 0,
        "b8": 0,
        "a8": 255,
        "h": 0.0,
        "s": 0.0,
        "v": 0.0
      },
      "Hsl": {
        "H": 1.3913767193951543E-08,
        "S": "NaN",
        "L": 0.0
      },
      "Lab": {
        "L": 0.0,
        "a": 0.0,
        "b": 0.0
      }
    },
    {
      "Color": {
        "r": 0.163255334,
        "g": 0.265781254,
        "b": 0.352643669,
        "a": 1.0,
        "r8": 42,
        "g8": 68,
        "b8": 90,
        "a8": 255,
        "h": 0.5764412,
        "s": 0.537053,
        "v": 0.352643669
      },
      "Hsl": {
        "H": 0.66148339080186058,
        "S": 0.24559690230536751,
        "L": 0.5681361589549303
      },
      "Lab": {
        "L": 0.628,
        "a": -0.023,
        "b": -0.037
      }
    },
    {
      "Color": {
        "r": 0.177505672,
        "g": 0.294490337,
        "b": 0.3886218,
        "a": 1.0,
        "r8": 45,
        "g8": 75,
        "b8": 99,
        "a8": 255,
        "h": 0.5743125,
        "s": 0.54324317,
        "v": 0.3886218
      },
      "Hsl": {
        "H": 0.65738691965787388,
        "S": 0.25839695236919452,
        "L": 0.59238064133254564
      },
      "Lab": {
        "L": 0.649,
        "a": -0.025,
        "b": -0.038
      }
    },
    {
      "Color": {
        "r": 0.204857334,
        "g": 0.333281249,
        "b": 0.43875277,
        "a": 1.0,
        "r8": 52,
        "g8": 85,
        "b8": 112,
        "a8": 255,
        "h": 0.575155735,
        "s": 0.533091664,
        "v": 0.43875277
      },
      "Hsl": {
        "H": 0.65927523800755772,
        "S": 0.26465871906004512,
        "L": 0.62474575197298821
      },
      "Lab": {
        "L": 0.677,
        "a": -0.025,
        "b": -0.039
      }
    },
    {
      "Color": {
        "r": 0.579593956,
        "g": 0.6511477,
        "b": 0.70856297,
        "a": 1.0,
        "r8": 148,
        "g8": 166,
        "b8": 181,
        "a8": 255,
        "h": 0.5741977,
        "s": 0.1820149,
        "v": 0.70856297
      },
      "Hsl": {
        "H": 0.66737532507307329,
        "S": 0.15967241753319975,
        "L": 0.8382038509990335
      },
      "Lab": {
        "L": 0.861,
        "a": -0.008,
        "b": -0.014
      }
    },
    {
      "Color": {
        "r": 1.0,
        "g": 1.0,
        "b": 0.99999994,
        "a": 1.0,
        "r8": 255,
        "g8": 255,
        "b8": 255,
        "a8": 255,
        "h": 0.166666672,
        "s": 5.96046448E-08,
        "v": 1.0
      },
      "Hsl": {
        "H": 1.3913767193951543E-08,
        "S": "NaN",
        "L": 0.99999999999999989
      },
      "Lab": {
        "L": 1.0,
        "a": 0.0,
        "b": 0.0
      }
    },
    {
      "Color": {
        "r": 0.262138128,
        "g": 0.3842744,
        "b": 0.484901,
        "a": 1.0,
        "r8": 67,
        "g8": 98,
        "b8": 124,
        "a8": 255,
        "h": 0.5752868,
        "s": 0.4593987,
        "v": 0.484901
      },
      "Hsl": {
        "H": 0.6619404686338578,
        "S": 0.23351623490492424,
        "L": 0.6664146988708286
      },
      "Lab": {
        "L": 0.713,
        "a": -0.021,
        "b": -0.034
      }
    },
    {
      "Color": {
        "r": 0.3420612,
        "g": 0.340430439,
        "b": 0.347773015,
        "a": 1.0,
        "r8": 87,
        "g8": 87,
        "b8": 89,
        "a8": 255,
        "h": 0.7036826,
        "s": 0.0211131312,
        "v": 0.347773015
      },
      "Hsl": {
        "H": 0.82379179981488893,
        "S": 0.012241560504113723,
        "L": 0.6502031630789411
      },
      "Lab": {
        "L": 0.699,
        "a": 0.001,
        "b": -0.002
      }
    },
    {
      "Color": {
        "r": 0.251922876,
        "g": 0.2515291,
        "b": 0.260155946,
        "a": 1.0,
        "r8": 64,
        "g8": 64,
        "b8": 66,
        "a8": 255,
        "h": 0.674274266,
        "s": 0.0331602953,
        "v": 0.260155946
      },
      "Hsl": {
        "H": 0.80120818279290207,
        "S": 0.016440557185788105,
        "L": 0.57275205342965207
      },
      "Lab": {
        "L": 0.632,
        "a": 0.001,
        "b": -0.003
      }
    },
    {
      "Color": {
        "r": 0.40911448,
        "g": 0.407277435,
        "b": 0.4155494,
        "a": 1.0,
        "r8": 104,
        "g8": 104,
        "b8": 106,
        "a8": 255,
        "h": 0.7036801,
        "s": 0.0199060868,
        "v": 0.4155494
      },
      "Hsl": {
        "H": 0.82379179981488893,
        "S": 0.013197576483954712,
        "L": 0.70002101769918457
      },
      "Lab": {
        "L": 0.742,
        "a": 0.001,
        "b": -0.002
      }
    },
    {
      "Color": {
        "r": 0.543752551,
        "g": 0.5453362,
        "b": 0.5496735,
        "a": 1.0,
        "r8": 139,
        "g8": 139,
        "b8": 140,
        "a8": 255,
        "h": 0.622089446,
        "s": 0.0107717523,
        "v": 0.5496735
      },
      "Hsl": {
        "H": 0.74999999304311638,
        "S": 0.0075097878366750925,
        "L": 0.78706602932517089
      },
      "Lab": {
        "L": 0.817,
        "a": 0.0,
        "b": -0.001
      }
    }
  ],
  "Tags": [],
  "Name": "random"
}